{
 "Anxious - Calm": 1,
 "Apolitical - Activist": 9,
 "Asexual - Hypersexual": 5,
 "Authoritarian - Libertarian": 8,
 "Cold - Loving": 5,
 "Competitive - Collaborative": 6,
 "Conservative - Progressive": 5,
 "Destitute - Wealthy": 4,
 "Difficult Childhood - Stable Childhood": 7,
 "Dysregulated - Composed": 6,
 "Education": "Secondary Education",
 "Gender Expression": "Transgender Female",
 "Genetic Population": "South Asian",
 "Gullible - Critical": 2,
 "Impulsive - Thoughtful": 4,
 "Incurious - Curious": 4,
 "Individualist - Collectivist": 4,
 "Introverted - Extroverted": 2,
 "Lazy - Ambitious": 10,
 "Misogynist - Egalitarian": 9,
 "Occupation": "Farming, Fishing, and Forestry",
 "Pessimistic - Optimistic": 9,
 "Racist - Inclusive": 3,
 "Religion": "Seventh-day Adventist Church",
 "Secular - Spiritual": 3,
 "Selfish - Generous": 2,
 "Sensitive - Robust": 6,
 "Serious - Playful": 4,
 "Sexuality": "Heterosexual",
 "Stubborn - Flexible": 1,
 "Teenager - Centenarian": 7,
 "Traditional - Contemporary": 2,
 "Unhealthy - Healthy": 7,
 "Unkind - Kind": 9,
 "Vain - Humble": 3,
 "Vengeful - Forgiving": 6,
 "Violent - Peaceful": 9
}