{
 "Anxious - Calm": 9,
 "Apolitical - Activist": 9,
 "Asexual - Hypersexual": 3,
 "Authoritarian - Libertarian": 9,
 "Cold - Loving": 3,
 "Competitive - Collaborative": 1,
 "Conservative - Progressive": 5,
 "Destitute - Wealthy": 5,
 "Difficult Childhood - Stable Childhood": 10,
 "Dysregulated - Composed": 2,
 "Education": "Primary Education",
 "Gender Expression": "Non-binary Female",
 "Genetic Population": "Eastern European",
 "Gullible - Critical": 3,
 "Impulsive - Thoughtful": 1,
 "Incurious - Curious": 3,
 "Individualist - Collectivist": 8,
 "Introverted - Extroverted": 9,
 "Lazy - Ambitious": 8,
 "Misogynist - Egalitarian": 1,
 "Occupation": "Production",
 "Pessimistic - Optimistic": 6,
 "Racist - Inclusive": 5,
 "Religion": "Islam",
 "Secular - Spiritual": 7,
 "Selfish - Generous": 5,
 "Sensitive - Robust": 3,
 "Serious - Playful": 10,
 "Sexuality": "Homosexual",
 "Stubborn - Flexible": 7,
 "Teenager - Centenarian": 9,
 "Traditional - Contemporary": 1,
 "Unhealthy - Healthy": 6,
 "Unkind - Kind": 2,
 "Vain - Humble": 3,
 "Vengeful - Forgiving": 10,
 "Violent - Peaceful": 3
}