{
 "Anxious - Calm": 5,
 "Apolitical - Activist": 4,
 "Asexual - Hypersexual": 4,
 "Authoritarian - Libertarian": 4,
 "Cold - Loving": 1,
 "Competitive - Collaborative": 2,
 "Conservative - Progressive": 1,
 "Destitute - Wealthy": 7,
 "Difficult Childhood - Stable Childhood": 9,
 "Dysregulated - Composed": 2,
 "Education": "Skilled Trade",
 "Gender Expression": "Genderqueer Female",
 "Genetic Population": "Pacific Islander",
 "Gullible - Critical": 1,
 "Impulsive - Thoughtful": 5,
 "Incurious - Curious": 4,
 "Individualist - Collectivist": 10,
 "Introverted - Extroverted": 7,
 "Lazy - Ambitious": 10,
 "Misogynist - Egalitarian": 6,
 "Occupation": "Business and Financial Operations",
 "Pessimistic - Optimistic": 2,
 "Racist - Inclusive": 2,
 "Religion": "Sikhism",
 "Secular - Spiritual": 4,
 "Selfish - Generous": 7,
 "Sensitive - Robust": 6,
 "Serious - Playful": 5,
 "Sexuality": "Heterosexual",
 "Stubborn - Flexible": 2,
 "Teenager - Centenarian": 5,
 "Traditional - Contemporary": 6,
 "Unhealthy - Healthy": 1,
 "Unkind - Kind": 1,
 "Vain - Humble": 6,
 "Vengeful - Forgiving": 2,
 "Violent - Peaceful": 2
}