{
 "Anxious - Calm": 5,
 "Apolitical - Activist": 8,
 "Asexual - Hypersexual": 8,
 "Authoritarian - Libertarian": 8,
 "Cold - Loving": 7,
 "Competitive - Collaborative": 10,
 "Conservative - Progressive": 8,
 "Destitute - Wealthy": 10,
 "Difficult Childhood - Stable Childhood": 1,
 "Dysregulated - Composed": 10,
 "Education": "Home Schooling",
 "Gender Expression": "Non-binary Male",
 "Genetic Population": "North African",
 "Gullible - Critical": 8,
 "Impulsive - Thoughtful": 6,
 "Incurious - Curious": 4,
 "Individualist - Collectivist": 7,
 "Introverted - Extroverted": 1,
 "Lazy - Ambitious": 8,
 "Misogynist - Egalitarian": 1,
 "Occupation": "Healthcare Support",
 "Pessimistic - Optimistic": 6,
 "Racist - Inclusive": 1,
 "Religion": "Jainism",
 "Secular - Spiritual": 9,
 "Selfish - Generous": 9,
 "Sensitive - Robust": 6,
 "Serious - Playful": 1,
 "Sexuality": "Bisexual",
 "Stubborn - Flexible": 6,
 "Teenager - Centenarian": 8,
 "Traditional - Contemporary": 7,
 "Unhealthy - Healthy": 8,
 "Unkind - Kind": 9,
 "Vain - Humble": 2,
 "Vengeful - Forgiving": 4,
 "Violent - Peaceful": 3
}