{
 "Anxious - Calm": 10,
 "Apolitical - Activist": 8,
 "Asexual - Hypersexual": 1,
 "Authoritarian - Libertarian": 8,
 "Cold - Loving": 9,
 "Competitive - Collaborative": 8,
 "Conservative - Progressive": 8,
 "Destitute - Wealthy": 1,
 "Difficult Childhood - Stable Childhood": 8,
 "Dysregulated - Composed": 7,
 "Education": "Skilled Trade",
 "Gender Expression": "Cisgendered Male",
 "Genetic Population": "North African",
 "Gullible - Critical": 5,
 "Impulsive - Thoughtful": 5,
 "Incurious - Curious": 6,
 "Individualist - Collectivist": 5,
 "Introverted - Extroverted": 8,
 "Lazy - Ambitious": 3,
 "Misogynist - Egalitarian": 8,
 "Occupation": "Architecture and Engineering",
 "Pessimistic - Optimistic": 2,
 "Racist - Inclusive": 10,
 "Religion": "Sikhism",
 "Secular - Spiritual": 8,
 "Selfish - Generous": 4,
 "Sensitive - Robust": 1,
 "Serious - Playful": 9,
 "Sexuality": "Bisexual",
 "Stubborn - Flexible": 4,
 "Teenager - Centenarian": 6,
 "Traditional - Contemporary": 8,
 "Unhealthy - Healthy": 7,
 "Unkind - Kind": 4,
 "Vain - Humble": 8,
 "Vengeful - Forgiving": 2,
 "Violent - Peaceful": 7
}