{
 "Anxious - Calm": 7,
 "Apolitical - Activist": 2,
 "Asexual - Hypersexual": 2,
 "Authoritarian - Libertarian": 4,
 "Cold - Loving": 5,
 "Competitive - Collaborative": 2,
 "Conservative - Progressive": 10,
 "Destitute - Wealthy": 7,
 "Difficult Childhood - Stable Childhood": 5,
 "Dysregulated - Composed": 2,
 "Education": "Secondary Education",
 "Gender Expression": "Cisgendered Female",
 "Genetic Population": "Pacific Islander",
 "Gullible - Critical": 8,
 "Impulsive - Thoughtful": 6,
 "Incurious - Curious": 3,
 "Individualist - Collectivist": 1,
 "Introverted - Extroverted": 9,
 "Lazy - Ambitious": 3,
 "Misogynist - Egalitarian": 9,
 "Occupation": "Homemaker, Domestic, Childcare",
 "Pessimistic - Optimistic": 4,
 "Racist - Inclusive": 7,
 "Religion": "Seventh-day Adventist Church",
 "Secular - Spiritual": 10,
 "Selfish - Generous": 8,
 "Sensitive - Robust": 10,
 "Serious - Playful": 5,
 "Sexuality": "Homosexual",
 "Stubborn - Flexible": 4,
 "Teenager - Centenarian": 9,
 "Traditional - Contemporary": 2,
 "Unhealthy - Healthy": 7,
 "Unkind - Kind": 7,
 "Vain - Humble": 5,
 "Vengeful - Forgiving": 8,
 "Violent - Peaceful": 3
}