{
 "Anxious - Calm": 7,
 "Apolitical - Activist": 2,
 "Asexual - Hypersexual": 7,
 "Authoritarian - Libertarian": 4,
 "Cold - Loving": 5,
 "Competitive - Collaborative": 3,
 "Conservative - Progressive": 5,
 "Destitute - Wealthy": 4,
 "Difficult Childhood - Stable Childhood": 2,
 "Dysregulated - Composed": 5,
 "Education": "Secondary Education",
 "Gender Expression": "Cisgendered Male",
 "Genetic Population": "Central American",
 "Gullible - Critical": 3,
 "Impulsive - Thoughtful": 1,
 "Incurious - Curious": 1,
 "Individualist - Collectivist": 3,
 "Introverted - Extroverted": 2,
 "Lazy - Ambitious": 5,
 "Misogynist - Egalitarian": 3,
 "Occupation": "Educational Instruction and Library",
 "Pessimistic - Optimistic": 4,
 "Racist - Inclusive": 10,
 "Religion": "Unitarian Universalism",
 "Secular - Spiritual": 3,
 "Selfish - Generous": 10,
 "Sensitive - Robust": 10,
 "Serious - Playful": 6,
 "Sexuality": "Homosexual",
 "Stubborn - Flexible": 3,
 "Teenager - Centenarian": 7,
 "Traditional - Contemporary": 10,
 "Unhealthy - Healthy": 6,
 "Unkind - Kind": 2,
 "Vain - Humble": 3,
 "Vengeful - Forgiving": 10,
 "Violent - Peaceful": 5
}